remote_compression/__init__.py
remote_compression/cli.py
remote_compression/compression.py
remote_compression/recurse.py
remote_compression/remote_compression.py
remote_compression/settings.py
remote_compression/ssh.py
remote_compression-0.1.7.dist-info/AUTHORS.md
remote_compression-0.1.7.dist-info/LICENSE
remote_compression-0.1.7.dist-info/METADATA
remote_compression-0.1.7.dist-info/WHEEL
remote_compression-0.1.7.dist-info/entry_points.txt
remote_compression-0.1.7.dist-info/RECORD
