Metadata-Version: 2.3
Name: remote-compression
Version: 0.1.7
Summary: rcomp helps to perform x265 video compression on remote server.
Author: Fabien Mathieu
Author-email: loufab@gmail.com
Requires-Python: >=3.10,<4.0
Classifier: Programming Language :: Python :: 3
Classifier: Programming Language :: Python :: 3.10
Classifier: Programming Language :: Python :: 3.11
Classifier: Programming Language :: Python :: 3.12
Classifier: Programming Language :: Python :: 3.13
Requires-Dist: click (>=8.1.7,<9.0.0)
Requires-Dist: dill (>=0.3.8,<0.4.0)
Requires-Dist: paramiko (>=3.5.0,<4.0.0)
Project-URL: Documentation, https://balouf.github.io/remote-compression
Project-URL: Repository, https://github.com/balouf/remote-compression
